currency_converter/__init__.py
currency_converter/converter.py
currency_converter_lite-0.1.0.dist-info/METADATA
currency_converter_lite-0.1.0.dist-info/WHEEL
currency_converter_lite-0.1.0.dist-info/top_level.txt
currency_converter_lite-0.1.0.dist-info/RECORD
