Metadata-Version: 2.1
Name: currency_converter_lite
Version: 0.1.0
Summary: A Library for currency conversion in Real Time
Home-page: https://github.com/AmeerTechsoft/currency-converter
Author: Ameer Adeigbe
Author-email: ameeradeigbe@gmail.com
Classifier: Programming Language :: Python :: 3
Classifier: License :: OSI Approved :: MIT License
Classifier: Operating System :: OS Independent
Requires-Python: >=3.8
Requires-Dist: yfinance
Requires-Dist: requests
Requires-Dist: beautifulsoup4
